lystorage/__init__.py
lystorage/aws_s3.py
quickstorage-0.1.0.dist-info/METADATA
quickstorage-0.1.0.dist-info/WHEEL
quickstorage-0.1.0.dist-info/RECORD
